pydwf/__init__.py
pydwf/__main__.py
pydwf/core/__init__.py
pydwf/core/dwf_device.py
pydwf/core/dwf_device_protocol_apis.py
pydwf/core/dwf_device_subapi.py
pydwf/core/dwf_library.py
pydwf/core/dwf_library_subapi.py
pydwf/core/api/__init__.py
pydwf/core/api/analog_impedance.py
pydwf/core/api/analog_in.py
pydwf/core/api/analog_io.py
pydwf/core/api/analog_out.py
pydwf/core/api/device_control.py
pydwf/core/api/device_enumeration.py
pydwf/core/api/digital_in.py
pydwf/core/api/digital_io.py
pydwf/core/api/digital_out.py
pydwf/core/api/protocol_can.py
pydwf/core/api/protocol_i2c.py
pydwf/core/api/protocol_spi.py
pydwf/core/api/protocol_swd.py
pydwf/core/api/protocol_uart.py
pydwf/core/api/spectrum.py
pydwf/core/auxiliary/__init__.py
pydwf/core/auxiliary/constants.py
pydwf/core/auxiliary/dwf_function_signatures.py
pydwf/core/auxiliary/enum_types.py
pydwf/core/auxiliary/exceptions.py
pydwf/core/auxiliary/typespec_ctypes.py
pydwf/data/__init__.py
pydwf/data/examples.py
pydwf/data/html_docs.py
pydwf/data/pdf_manual.py
pydwf/utilities/__init__.py
pydwf/utilities/configuration.py
pydwf/utilities/open_dwf_device.py
pydwf-1.1.17.dist-info/LICENSE
pydwf-1.1.17.dist-info/METADATA
pydwf-1.1.17.dist-info/WHEEL
pydwf-1.1.17.dist-info/top_level.txt
pydwf-1.1.17.dist-info/RECORD
