Metadata-Version: 2.1
Name: pydwf
Version: 1.1.17
Summary: A package to control Digilent Waveforms devices
Home-page: https://pypi.org/project/pydwf/
Author: Sidney Cadot
Author-email: sidney@jigsaw.nl
Project-URL: Source Repository, https://github.com/sidneycadot/pydwf/
Project-URL: Documentation, https://pydwf.readthedocs.io/en/latest/
Classifier: Programming Language :: Python :: 3 :: Only
Classifier: License :: OSI Approved :: MIT License
Classifier: Topic :: Scientific/Engineering
Requires-Python: >=3.6
License-File: LICENSE
Requires-Dist: numpy
